Metadata-Version: 1.0
Name: pip-debugger-parikshit
Version: 1.0.0
Summary: Debugging pip
Home-page: UNKNOWN
Author: UNKNOWN
Author-email: UNKNOWN
License: UNKNOWN
Platform: UNKNOWN
